investec_open_api/__init__.py
investec_open_api/client.py
investec_open_api-0.0.3.dist-info/METADATA
investec_open_api-0.0.3.dist-info/WHEEL
investec_open_api-0.0.3.dist-info/licenses/LICENSE
investec_open_api-0.0.3.dist-info/RECORD
