Metadata-Version: 2.1
Name: investec_open_api
Version: 0.0.3
Summary: A connector for the Investec Open API
Project-URL: Homepage, https://github.com/devinpearson/investec-open-api-python
Project-URL: Bug Tracker, https://github.com/devinpearson/investec-open-api-python/issues
Author-email: Devin Pearson <devin@blackhat.co.za>
License-File: LICENSE
Classifier: License :: OSI Approved :: MIT License
Classifier: Operating System :: OS Independent
Classifier: Programming Language :: Python :: 3
Requires-Python: >=3.7
